neurdflib_jsonld-0.4.1.dist-info/METADATA
neurdflib_jsonld-0.4.1.dist-info/RECORD
neurdflib_jsonld-0.4.1.dist-info/WHEEL
neurdflib_jsonld-0.4.1.dist-info/entry_points.txt
neurdflib_jsonld-0.4.1.dist-info/top_level.txt
rdflib_jsonld/__init__.py
rdflib_jsonld/_compat.py
rdflib_jsonld/context.py
rdflib_jsonld/errors.py
rdflib_jsonld/keys.py
rdflib_jsonld/parser.py
rdflib_jsonld/serializer.py
rdflib_jsonld/util.py
