Metadata-Version: 2.1
Name: neurdflib-jsonld
Version: 0.4.1
Summary: TEMP RELEASE OF rdflib extension adding JSON-LD parser and serializer
Home-page: https://github.com/tgbugs/rdflib-jsonld
Maintainer: tgbugs
License: BSD
Platform: any
Classifier: Programming Language :: Python
Classifier: Programming Language :: Python :: 2
Classifier: Programming Language :: Python :: 2.7
Classifier: Programming Language :: Python :: 3
Classifier: Programming Language :: Python :: 3.3
Classifier: Programming Language :: Python :: 3.4
Classifier: Programming Language :: Python :: 3.5
Classifier: Programming Language :: Python :: 3.6
Classifier: License :: OSI Approved :: BSD License
Classifier: Topic :: Software Development :: Libraries :: Python Modules
Classifier: Operating System :: OS Independent
Classifier: Natural Language :: English
Requires-Dist: neurdflib (>=5.0.0)
